{"importBase":"import","nativeBase":"native","name":"resources","deps":["internal"],"uuids":["3aKkf1buFGDbTSh4R3FLI3","59w8gjxQNLsLDeA4gLo5Oa","a7DzHxXSJLFoTm7JpOLu6N","b3rVA0iBZJNrjX8wvUdYKC","ccQgxVNOlHab/riS3gkXXj","e3fCFVro1MC5KC+hLmKE34","0cr5lRzwZOGbNQnaIr2kP5","16dc38bb3","20g1ukYUVPvKWKBRznAKo+","297ljFkphAs6EHYvP+VTZl","46Dp/ec8JHXYck2haygTcw","49RbiwWOJMR40UWwYNWyMw","54TknWPwVPqJqeCR+Y/Czo","57VJow/u1Kv5rZorYfc61W","666EaND0RI+aVQrKGc+IRd","70ZMst5YxJ4J+GWbHPzO71","74T2zRlktAQo9Bd0MrMwIA","7f1MBR5xRHKJldnjJgxsT8","82Wm+sxcxEyIhg4Dbdj3Zh","845O002f9HWrvQm9cWAHeo","89Smonp2RPRZNEvtD2e1N8","91sTAe75hL6rKuh6itkpeA","95EkngnxZFbYuFpsqVTaFr","9a9zg05QhESbZe2v5pNicq","abNpvbSBlNQIUVuXmE3NeL","b7MFJ8MjNBwqr3fNq1j5dJ","b9IzWPatpFg6M08FCemFzM","caWF+ApHpG5rTHwamErPF7","cdwDhLrDNGvKRP4Z29P2UD","e2KGtQzVRJI4u/9f0V3VNX","e66WJuLBZF8IBHAqB7AByD","efSsXDdFNK4pJFHclRg+0S","f1hv0edm9OY6+jGvUCv0ai","08cWLPBRJHc7c1SCzmSvIq@f9941","0b28c2092","0ecB6j/SVEvpjOVfgREWQw@f9941","11sJNhdEhICapemC8pCkov@f9941","16zmEfB7ZAYb2RPYRXM4Lz@f9941","16dc38bb3@6c48a","1c83plNddBb5HLB0If+hC2@f9941","20g1ukYUVPvKWKBRznAKo+@6c48a","20g1ukYUVPvKWKBRznAKo+@f9941","20wnzfPERAurFHtfS8GGA1@f9941","2aTMRVh8dF/5WcVorfyv6i@f9941","2ar7xRvoJEWIM5PRgp4810@f9941","2btRCcvypBY44f52pziyrh@f9941","2cniFnVQBDvL+pQo53/kaf@f9941","49RbiwWOJMR40UWwYNWyMw@6c48a","49RbiwWOJMR40UWwYNWyMw@f9941","4aP2H1hlxAIJfAFgmbyd/S@f9941","4do+7LDzhMs7IiFD4RZXPT@f9941","53mH6/UqpAvZ2RBAcbjZqd@f9941","54TknWPwVPqJqeCR+Y/Czo@6c48a","54TknWPwVPqJqeCR+Y/Czo@f9941","5456cvEsRHVb0fR+uHOe5e@f9941","59q9zo921MQYjvkC1V1XfE@f9941","5e5QIjAYJH9Yi2mAJct0O7@f9941","729YydO7JAfof5c4K9QE83@f9941","73P9GSAlhLD7WP9fXFYibi","74T2zRlktAQo9Bd0MrMwIA@6c48a","74T2zRlktAQo9Bd0MrMwIA@f9941","76xBd3amtA/5TeHpsntGvh@f9941","7cYNHasNJNyJ1ppCjHBy7Q@f9941","84veg4A51FAI6kLlKekdfj@f9941","85jESVxuxLILHaghr3beho@f9941","88m4oqSetK+5Y1fsOSfZ1p@f9941","89Smonp2RPRZNEvtD2e1N8@6c48a","8dYAgeh/hIkIyY2CY/m3GL@f9941","95EkngnxZFbYuFpsqVTaFr@6c48a","95EkngnxZFbYuFpsqVTaFr@f9941","9dxX15dZ1O8oAloVtIcU7n@f9941","aet9pvjMlFAZeBa3zWCaNN@f9941","b51hFfA3BNfKrTwZTMcc+Y","b7MFJ8MjNBwqr3fNq1j5dJ@6c48a","b7MFJ8MjNBwqr3fNq1j5dJ@f9941","bdhifnMy5KhK0bSmU0wFIc","bfcexd3gtGB7XjPtsJ31Kn@f9941","c8ztdt5h9MHofJa+J6eUYQ@f9941","cdwDhLrDNGvKRP4Z29P2UD@6c48a","d0s7WyNfNM/Kqda9PK10aS@f9941","d5DOZmBIpF6KLKFvDaOq9P@f9941","dc9JtGfGVDMK1MTgXEbKBh","ddxZa2lyxA9JepNkF0flSI@f9941","eaX+WsmopMJYPkj2ALFiZU@f9941","ecFHCc+4tNUKtMlK6XzHM4@f9941","f2SOTnGoVP4Y/nCO4viWyr","f4mvVbuttBZbA31btzNRcv@f9941","fcDhQbOb5C4LFVJmhoW/kg@f9941","fdoJXLgx1GAa2UhGATlj3o","ffl+R7GiRNZ6YEbJbWIAdK@f9941"],"paths":{"0":["sound/bg3",2,1],"1":["sound/buttonClick",2,1],"2":["sound/bg1",2,1],"3":["sound/countDown",2,1],"4":["sound/bg4",2,1],"5":["sound/bg2",2,1],"6":["prefab/fortuneCommon/FortuneSetAuto",3,1],"9":["prefab/fortuneCommon/FortuneHistory",3,1],"10":["prefab/public/showToast",3,1],"13":["effect/LineSprite",0,1],"14":["effect/graySpine",1,1],"15":["effect/graySprite",1,1],"17":["effect/rMask",0,1],"18":["prefab/fortuneCommon/FortuneSetBase",3,1],"19":["effect/rMask",1,1],"21":["effect/graySprite",0,1],"23":["effect/graySpine",0,1],"24":["prefab/public/wait2",3,1],"26":["effect/LineSprite",1,1],"27":["prefab/fortuneCommon/FortuneRank",3,1],"29":["prefab/public/wait1",3,1],"30":["prefab/public/showTips",3,1],"31":["prefab/public/showNetTips",3,1]},"scenes":{},"packs":{"0b28c2092":[33,6,35,36,37,7,38,39,8,40,41,42,9,43,44,45,46,0,10,11,47,48,49,50,51,12,52,53,54,13,55,1,56,14,15,57,58,16,59,60,61,62,17,18,63,19,64,65,20,66,67,21,22,68,69,23,70,2,24,71,3,25,73,74,26,75,76,77,27,4,28,78,79,80,81,82,29,5,30,83,84,31,32,85,86,87,89]},"versions":{"import":[34,"684d9"],"native":[7,"5cdba",8,"90cf4",0,"14ff7",11,"004e2",12,"83fcc",1,"94f70",16,"c7fa7",20,"c8451",22,"c06a9",2,"2f451",3,"ac2ff",25,"cdbc9",4,"60ee6",28,"1f904",5,"b96b1",32,"d9076"]},"redirect":[72,"0",88,"0"],"debug":false,"extensionMap":{},"hasPreloadScript":true,"dependencyRelationships":{},"types":["cc.EffectAsset","cc.Material","cc.AudioClip","cc.Prefab"]}